{"swagger":"2.0","info":{"description":"模板项目","version":"1.0.0","title":"hlj-proj","termsOfService":"http://localhost:8888/","license":{"name":"demo","url":"http://localhost:8888/"}},"host":"localhost:8888","basePath":"/","tags":[{"name":"demo-controller","description":"demo控制器"},{"name":"vialidate-controller","description":"demo控制器"}],"paths":{"/hlj/demo/get":{"get":{"tags":["demo-controller"],"summary":"demo实体","description":"demo实体","operationId":"getUsingGET","consumes":["application/json","application/x-www-form-urlencoded"],"produces":["application/json","application/json;charset=utf-8"],"parameters":[{"name":"name","in":"query","description":"姓名","required":false,"type":"string"},{"name":"age","in":"query","description":"年龄","required":false,"type":"integer","format":"int32"},{"name":"phone","in":"query","description":"手机号","required":false,"type":"string"},{"name":"email","in":"query","description":"邮箱","required":false,"type":"string"}],"responses":{"200":{"description":"访问正常","schema":{"$ref":"#/definitions/demo实体类"}},"301":{"description":"逻辑错误"},"401":{"description":"未认证"},"403":{"description":"禁止访问"},"404":{"description":"url错误"},"500":{"description":"系统错误"}}}},"/hlj/validate":{"post":{"tags":["vialidate-controller"],"summary":"Post接口","description":"Post接口","operationId":"postUsingPOST","consumes":["application/json","application/x-www-form-urlencoded"],"produces":["application/json","application/json;charset=utf-8"],"parameters":[{"in":"body","name":"javaBean","description":"javaBean","required":true,"schema":{"$ref":"#/definitions/JavaBean"}}],"responses":{"200":{"description":"访问正常","schema":{"$ref":"#/definitions/ResponseBean"}},"201":{"description":"Created"},"301":{"description":"逻辑错误"},"401":{"description":"未认证"},"403":{"description":"禁止访问"},"404":{"description":"url错误"},"500":{"description":"系统错误"}}}}},"definitions":{"InnerBean":{"type":"object","properties":{"innerNname":{"type":"string"}}},"JavaBean":{"type":"object","properties":{"assertFalse":{"type":"boolean"},"fatherString":{"type":"string"},"innerBean":{"$ref":"#/definitions/InnerBean"},"list":{"type":"array","items":{"type":"string"}},"myDec":{"type":"number"},"myName":{"type":"string"},"name":{"type":"string"},"strDecimal":{"type":"string"},"strDigts":{"type":"string"},"strLength":{"type":"string"},"strNum":{"type":"string"},"strRange":{"type":"string"},"testGroup":{"type":"string"}}},"ResponseBean":{"type":"object","properties":{"code":{"type":"integer","format":"int32"},"date":{"type":"string"},"msg":{"type":"string"},"result":{"type":"object"},"success":{"type":"boolean"}}},"demo实体类":{"type":"object","properties":{"age":{"type":"integer","format":"int32","description":"年龄"},"email":{"type":"string","description":"邮箱"},"name":{"type":"string","description":"姓名"},"phone":{"type":"string","description":"手机号"}}}}}